tossnturn/__init__.py
tossnturn/gui.py
tossnturn-0.2.1.dist-info/METADATA
tossnturn-0.2.1.dist-info/WHEEL
tossnturn-0.2.1.dist-info/entry_points.txt
tossnturn-0.2.1.dist-info/licenses/LICENSE
tossnturn-0.2.1.dist-info/RECORD
